gamerinsta/__init__.py
gamerinsta/tokens.py
gamerinsta-0.0.5.dist-info/LICENSE
gamerinsta-0.0.5.dist-info/METADATA
gamerinsta-0.0.5.dist-info/WHEEL
gamerinsta-0.0.5.dist-info/top_level.txt
gamerinsta-0.0.5.dist-info/RECORD
