Metadata-Version: 2.1
Name: gamerinsta
Version: 0.0.5
Summary: Instagram Android Api For Login 
Author: Gamer
Author-email: godxgamer0192@gmail.com
Keywords: Instagram,login
Classifier: Development Status :: 1 - Planning
Classifier: Intended Audience :: Developers
Classifier: Programming Language :: Python :: 3
Classifier: Operating System :: Unix
Classifier: Operating System :: MacOS :: MacOS X
Classifier: Operating System :: Microsoft :: Windows
License-File: LICENSE
Requires-Dist: httpx
Requires-Dist: user-agent
Requires-Dist: uuid
Requires-Dist: requests
